nudnik/__init__.py
nudnik/cli.py
nudnik/client.py
nudnik/entity_pb2.py
nudnik/entity_pb2_grpc.py
nudnik/etcd_server.py
nudnik/grpc_server.py
nudnik/http2_server.py
nudnik/load.py
nudnik/metrics.py
nudnik/outputs.py
nudnik/ruok2.py
nudnik/ruok3.py
nudnik/stats.py
nudnik/test.py
nudnik/utils.py
nudnik/tests/__init__.py
nudnik-0.0.33.data/scripts/nudnik
nudnik-0.0.33.dist-info/LICENSE
nudnik-0.0.33.dist-info/METADATA
nudnik-0.0.33.dist-info/WHEEL
nudnik-0.0.33.dist-info/top_level.txt
nudnik-0.0.33.dist-info/RECORD
