Metadata-Version: 2.1
Name: nudnik
Version: 0.0.33
Summary: gRPC load-balancing testing tool
Home-page: https://github.com/salosh/nudnik.git
Author: Salo Shp
Author-email: support@salosh.org
License: GPLv3
Platform: UNKNOWN
Classifier: Environment :: Console
Classifier: Intended Audience :: System Administrators
Classifier: Programming Language :: Python
Classifier: Topic :: System :: Distributed Computing
Classifier: License :: OSI Approved :: GNU General Public License v3 or later (GPLv3+)
Classifier: Natural Language :: English
Classifier: Operating System :: OS Independent
Requires-Dist: PyYAML (>=5.1.1)
Requires-Dist: etcd3 (>=0.8.1)
Requires-Dist: grpcio (>=1.21.1)
Requires-Dist: protobuf (>=3.8.0)
Requires-Dist: requests-unixsocket (>=0.1.5)
Requires-Dist: psutil (>=5.6.3)
Requires-Dist: requests (>=2.22.0)
